pyloggor/__init__.py
pyloggor/pyloggor.py
pyloggor-1.2.dist-info/LICENSE
pyloggor-1.2.dist-info/METADATA
pyloggor-1.2.dist-info/WHEEL
pyloggor-1.2.dist-info/top_level.txt
pyloggor-1.2.dist-info/RECORD
