Metadata-Version: 2.1
Name: pyloggor
Version: 1.2
Summary: An incredibly versatile yet simple logging system.
Home-page: https://www.github.com/PrivatePandaCO/pyloggor
Author: Parth Mittal
Author-email: parth@privatepanda.co
License: MIT
Project-URL: Documentation, https://github.com/PrivatePandaCO/pyloggor/blob/master/README.md
Project-URL: Github, https://github.com/PrivatePandaCO/pyloggor
License-File: LICENSE
